MANIFEST.in
README.rst
setup.py
getalbum/__init__.py
getalbum/__main__.py
getalbum/getalbum.py
getalbum.egg-info/PKG-INFO
getalbum.egg-info/SOURCES.txt
getalbum.egg-info/dependency_links.txt
getalbum.egg-info/entry_points.txt
getalbum.egg-info/requires.txt
getalbum.egg-info/top_level.txt